latex_gen/__init__.py
latex_gen/example_latex.py
latex_gen/latex_gen.py
novokshanovLatexGen-0.4.0.dist-info/METADATA
novokshanovLatexGen-0.4.0.dist-info/WHEEL
novokshanovLatexGen-0.4.0.dist-info/top_level.txt
novokshanovLatexGen-0.4.0.dist-info/RECORD
