Metadata-Version: 2.1
Name: novokshanovLatexGen
Version: 0.4.0
Summary: Library to generate LaTeX code for tables and images.
Home-page: UNKNOWN
Author: novokshanov.e
Author-email: novokshanov.eugene@yandex.ru
License: UNKNOWN
Platform: UNKNOWN
